discountr/API.py
discountr/__init__.py
discountr/helpers.py
discountr/models.py
discountr_client-0.0.10.dist-info/LICENSE
discountr_client-0.0.10.dist-info/METADATA
discountr_client-0.0.10.dist-info/WHEEL
discountr_client-0.0.10.dist-info/top_level.txt
discountr_client-0.0.10.dist-info/RECORD
